{"msg":"操作成功","code":200,"data":[{"createBy":null,"createTime":"2025-11-25 17:21:21","updateBy":null,"updateTime":null,"remark":null,"menuId":2000,"menuName":"客户设置","parentName":null,"parentId":0,"orderNum":1,"path":"customer","component":null,"query":null,"routeName":"","isFrame":"1","isCache":"0","menuType":"M","visible":"0","status":"0","perms":"","icon":"peoples","children":[]},{"createBy":null,"createTime":"2025-11-28 11:38:25","updateBy":null,"updateTime":null,"remark":null,"menuId":2018,"menuName":"测序管理","parentName":null,"parentId":0,"orderNum":2,"path":"sequencing","component":null,"query":null,"routeName":"","isFrame":"1","isCache":"0","menuType":"M","visible":"0","status":"0","perms":"","icon":"example","children":[]},{"createBy":null,"createTime":"2025-11-19 20:51:19","updateBy":null,"updateTime":null,"remark":null,"menuId":4,"menuName":"有康官网","parentName":null,"parentId":0,"orderNum":3,"path":"http://youkang.vip","component":null,"query":"","routeName":"","isFrame":"0","isCache":"0","menuType":"M","visible":"0","status":"0","perms":"","icon":"guide","children":[]},{"createBy":null,"createTime":"2026-01-06 23:36:37","updateBy":null,"updateTime":null,"remark":null,"menuId":2033,"menuName":"历史数据","parentName":null,"parentId":0,"orderNum":4,"path":"history","component":null,"query":null,"routeName":"","isFrame":"1","isCache":"0","menuType":"M","visible":"0","status":"0","perms":"","icon":"list","children":[]},{"createBy":null,"createTime":"2026-04-13 23:57:56","updateBy":null,"updateTime":null,"remark":null,"menuId":2052,"menuName":"合成管理","parentName":null,"parentId":0,"orderNum":4,"path":"synthesis","component":null,"query":null,"routeName":"","isFrame":"1","isCache":"0","menuType":"M","visible":"0","status":"0","perms":"","icon":"build","children":[]},{"createBy":null,"createTime":"2025-11-19 20:51:19","updateBy":null,"updateTime":null,"remark":null,"menuId":1,"menuName":"系统管理","parentName":null,"parentId":0,"orderNum":5,"path":"system","component":null,"query":"","routeName":"","isFrame":"1","isCache":"0","menuType":"M","visible":"0","status":"0","perms":"","icon":"system","children":[]},{"createBy":null,"createTime":"2025-11-19 20:51:19","updateBy":null,"updateTime":null,"remark":null,"menuId":2,"menuName":"系统监控","parentName":null,"parentId":0,"orderNum":6,"path":"monitor","component":null,"query":"","routeName":"","isFrame":"1","isCache":"0","menuType":"M","visible":"0","status":"0","perms":"","icon":"monitor","children":[]},{"createBy":null,"createTime":"2025-11-19 20:51:19","updateBy":null,"updateTime":null,"remark":null,"menuId":3,"menuName":"系统工具","parentName":null,"parentId":0,"orderNum":7,"path":"tool","component":null,"query":"","routeName":"","isFrame":"1","isCache":"0","menuType":"M","visible":"0","status":"0","perms":"","icon":"tool","children":[]},{"createBy":null,"createTime":"2025-11-19 20:51:19","updateBy":null,"updateTime":null,"remark":null,"menuId":100,"menuName":"用户管理","parentName":null,"parentId":1,"orderNum":1,"path":"user","component":"system/user/index","query":"","routeName":"","isFrame":"1","isCache":"0","menuType":"C","visible":"0","status":"0","perms":"system:user:list","icon":"user","children":[]},{"createBy":null,"createTime":"2025-11-19 20:51:19","updateBy":null,"updateTime":null,"remark":null,"menuId":101,"menuName":"角色管理","parentName":null,"parentId":1,"orderNum":2,"path":"role","component":"system/role/index","query":"","routeName":"","isFrame":"1","isCache":"0","menuType":"C","visible":"0","status":"0","perms":"system:role:list","icon":"peoples","children":[]},{"createBy":null,"createTime":"2025-11-19 20:51:19","updateBy":null,"updateTime":null,"remark":null,"menuId":102,"menuName":"菜单管理","parentName":null,"parentId":1,"orderNum":3,"path":"menu","component":"system/menu/index","query":"","routeName":"","isFrame":"1","isCache":"0","menuType":"C","visible":"0","status":"0","perms":"system:menu:list","icon":"tree-table","children":[]},{"createBy":null,"createTime":"2025-11-19 20:51:19","updateBy":null,"updateTime":null,"remark":null,"menuId":103,"menuName":"部门管理","parentName":null,"parentId":1,"orderNum":4,"path":"dept","component":"system/dept/index","query":"","routeName":"","isFrame":"1","isCache":"0","menuType":"C","visible":"0","status":"0","perms":"system:dept:list","icon":"tree","children":[]},{"createBy":null,"createTime":"2025-11-19 20:51:19","updateBy":null,"updateTime":null,"remark":null,"menuId":104,"menuName":"岗位管理","parentName":null,"parentId":1,"orderNum":5,"path":"post","component":"system/post/index","query":"","routeName":"","isFrame":"1","isCache":"0","menuType":"C","visible":"0","status":"0","perms":"system:post:list","icon":"post","children":[]},{"createBy":null,"createTime":"2025-11-19 20:51:19","updateBy":null,"updateTime":null,"remark":null,"menuId":105,"menuName":"字典管理","parentName":null,"parentId":1,"orderNum":6,"path":"dict","component":"system/dict/index","query":"","routeName":"","isFrame":"1","isCache":"0","menuType":"C","visible":"0","status":"0","perms":"system:dict:list","icon":"dict","children":[]},{"createBy":null,"createTime":"2025-11-19 20:51:19","updateBy":null,"updateTime":null,"remark":null,"menuId":106,"menuName":"参数设置","parentName":null,"parentId":1,"orderNum":7,"path":"config","component":"system/config/index","query":"","routeName":"","isFrame":"1","isCache":"0","menuType":"C","visible":"0","status":"0","perms":"system:config:list","icon":"edit","children":[]},{"createBy":null,"createTime":"2025-11-19 20:51:19","updateBy":null,"updateTime":null,"remark":null,"menuId":107,"menuName":"通知公告","parentName":null,"parentId":1,"orderNum":8,"path":"notice","component":"system/notice/index","query":"","routeName":"","isFrame":"1","isCache":"0","menuType":"C","visible":"0","status":"0","perms":"system:notice:list","icon":"message","children":[]},{"createBy":null,"createTime":"2025-11-19 20:51:19","updateBy":null,"updateTime":null,"remark":null,"menuId":108,"menuName":"日志管理","parentName":null,"parentId":1,"orderNum":9,"path":"log","component":"","query":"","routeName":"","isFrame":"1","isCache":"0","menuType":"M","visible":"0","status":"0","perms":"","icon":"log","children":[]},{"createBy":null,"createTime":"2025-11-19 20:51:19","updateBy":null,"updateTime":null,"remark":null,"menuId":109,"menuName":"在线用户","parentName":null,"parentId":2,"orderNum":1,"path":"online","component":"monitor/online/index","query":"","routeName":"","isFrame":"1","isCache":"0","menuType":"C","visible":"0","status":"0","perms":"monitor:online:list","icon":"online","children":[]},{"createBy":null,"createTime":"2025-11-19 20:51:19","updateBy":null,"updateTime":null,"remark":null,"menuId":110,"menuName":"定时任务","parentName":null,"parentId":2,"orderNum":2,"path":"job","component":"monitor/job/index","query":"","routeName":"","isFrame":"1","isCache":"0","menuType":"C","visible":"0","status":"0","perms":"monitor:job:list","icon":"job","children":[]},{"createBy":null,"createTime":"2025-11-19 20:51:20","updateBy":null,"updateTime":null,"remark":null,"menuId":111,"menuName":"数据监控","parentName":null,"parentId":2,"orderNum":3,"path":"druid","component":"monitor/druid/index","query":"","routeName":"","isFrame":"1","isCache":"0","menuType":"C","visible":"0","status":"0","perms":"monitor:druid:list","icon":"druid","children":[]},{"createBy":null,"createTime":"2025-11-19 20:51:20","updateBy":null,"updateTime":null,"remark":null,"menuId":112,"menuName":"服务监控","parentName":null,"parentId":2,"orderNum":4,"path":"server","component":"monitor/server/index","query":"","routeName":"","isFrame":"1","isCache":"0","menuType":"C","visible":"0","status":"0","perms":"monitor:server:list","icon":"server","children":[]},{"createBy":null,"createTime":"2025-11-19 20:51:20","updateBy":null,"updateTime":null,"remark":null,"menuId":113,"menuName":"缓存监控","parentName":null,"parentId":2,"orderNum":5,"path":"cache","component":"monitor/cache/index","query":"","routeName":"","isFrame":"1","isCache":"0","menuType":"C","visible":"0","status":"0","perms":"monitor:cache:list","icon":"redis","children":[]},{"createBy":null,"createTime":"2025-11-19 20:51:20","updateBy":null,"updateTime":null,"remark":null,"menuId":114,"menuName":"缓存列表","parentName":null,"parentId":2,"orderNum":6,"path":"cacheList","component":"monitor/cache/list","query":"","routeName":"","isFrame":"1","isCache":"0","menuType":"C","visible":"0","status":"0","perms":"monitor:cache:list","icon":"redis-list","children":[]},{"createBy":null,"createTime":"2025-11-19 20:51:20","updateBy":null,"updateTime":null,"remark":null,"menuId":115,"menuName":"表单构建","parentName":null,"parentId":3,"orderNum":1,"path":"build","component":"tool/build/index","query":"","routeName":"","isFrame":"1","isCache":"0","menuType":"C","visible":"0","status":"0","perms":"tool:build:list","icon":"build","children":[]},{"createBy":null,"createTime":"2025-11-19 20:51:20","updateBy":null,"updateTime":null,"remark":null,"menuId":116,"menuName":"代码生成","parentName":null,"parentId":3,"orderNum":2,"path":"gen","component":"tool/gen/index","query":"","routeName":"","isFrame":"1","isCache":"0","menuType":"C","visible":"0","status":"0","perms":"tool:gen:list","icon":"code","children":[]},{"createBy":null,"createTime":"2025-11-19 20:51:20","updateBy":null,"updateTime":null,"remark":null,"menuId":117,"menuName":"系统接口","parentName":null,"parentId":3,"orderNum":3,"path":"swagger","component":"tool/swagger/index","query":"","routeName":"","isFrame":"1","isCache":"0","menuType":"C","visible":"0","status":"0","perms":"tool:swagger:list","icon":"swagger","children":[]},{"createBy":null,"createTime":"2026-03-28 20:22:52","updateBy":null,"updateTime":null,"remark":null,"menuId":2039,"menuName":"菜单工具","parentName":null,"parentId":3,"orderNum":5,"path":"menuimport","component":"tool/menuimport/index","query":null,"routeName":"","isFrame":"1","isCache":"0","menuType":"C","visible":"0","status":"0","perms":"tool:menuimport:list","icon":"tool","children":[]},{"createBy":null,"createTime":"2025-11-19 20:51:20","updateBy":null,"updateTime":null,"remark":null,"menuId":1000,"menuName":"用户查询","parentName":null,"parentId":100,"orderNum":1,"path":"","component":"","query":"","routeName":"","isFrame":"1","isCache":"0","menuType":"F","visible":"0","status":"0","perms":"system:user:query","icon":"#","children":[]},{"createBy":null,"createTime":"2025-11-19 20:51:20","updateBy":null,"updateTime":null,"remark":null,"menuId":1001,"menuName":"用户新增","parentName":null,"parentId":100,"orderNum":2,"path":"","component":"","query":"","routeName":"","isFrame":"1","isCache":"0","menuType":"F","visible":"0","status":"0","perms":"system:user:add","icon":"#","children":[]},{"createBy":null,"createTime":"2025-11-19 20:51:20","updateBy":null,"updateTime":null,"remark":null,"menuId":1002,"menuName":"用户修改","parentName":null,"parentId":100,"orderNum":3,"path":"","component":"","query":"","routeName":"","isFrame":"1","isCache":"0","menuType":"F","visible":"0","status":"0","perms":"system:user:edit","icon":"#","children":[]},{"createBy":null,"createTime":"2025-11-19 20:51:20","updateBy":null,"updateTime":null,"remark":null,"menuId":1003,"menuName":"用户删除","parentName":null,"parentId":100,"orderNum":4,"path":"","component":"","query":"","routeName":"","isFrame":"1","isCache":"0","menuType":"F","visible":"0","status":"0","perms":"system:user:remove","icon":"#","children":[]},{"createBy":null,"createTime":"2025-11-19 20:51:20","updateBy":null,"updateTime":null,"remark":null,"menuId":1004,"menuName":"用户导出","parentName":null,"parentId":100,"orderNum":5,"path":"","component":"","query":"","routeName":"","isFrame":"1","isCache":"0","menuType":"F","visible":"0","status":"0","perms":"system:user:export","icon":"#","children":[]},{"createBy":null,"createTime":"2025-11-19 20:51:20","updateBy":null,"updateTime":null,"remark":null,"menuId":1005,"menuName":"用户导入","parentName":null,"parentId":100,"orderNum":6,"path":"","component":"","query":"","routeName":"","isFrame":"1","isCache":"0","menuType":"F","visible":"0","status":"0","perms":"system:user:import","icon":"#","children":[]},{"createBy":null,"createTime":"2025-11-19 20:51:20","updateBy":null,"updateTime":null,"remark":null,"menuId":1006,"menuName":"重置密码","parentName":null,"parentId":100,"orderNum":7,"path":"","component":"","query":"","routeName":"","isFrame":"1","isCache":"0","menuType":"F","visible":"0","status":"0","perms":"system:user:resetPwd","icon":"#","children":[]},{"createBy":null,"createTime":"2025-11-19 20:51:20","updateBy":null,"updateTime":null,"remark":null,"menuId":1007,"menuName":"角色查询","parentName":null,"parentId":101,"orderNum":1,"path":"","component":"","query":"","routeName":"","isFrame":"1","isCache":"0","menuType":"F","visible":"0","status":"0","perms":"system:role:query","icon":"#","children":[]},{"createBy":null,"createTime":"2025-11-19 20:51:20","updateBy":null,"updateTime":null,"remark":null,"menuId":1008,"menuName":"角色新增","parentName":null,"parentId":101,"orderNum":2,"path":"","component":"","query":"","routeName":"","isFrame":"1","isCache":"0","menuType":"F","visible":"0","status":"0","perms":"system:role:add","icon":"#","children":[]},{"createBy":null,"createTime":"2025-11-19 20:51:20","updateBy":null,"updateTime":null,"remark":null,"menuId":1009,"menuName":"角色修改","parentName":null,"parentId":101,"orderNum":3,"path":"","component":"","query":"","routeName":"","isFrame":"1","isCache":"0","menuType":"F","visible":"0","status":"0","perms":"system:role:edit","icon":"#","children":[]},{"createBy":null,"createTime":"2025-11-19 20:51:20","updateBy":null,"updateTime":null,"remark":null,"menuId":1010,"menuName":"角色删除","parentName":null,"parentId":101,"orderNum":4,"path":"","component":"","query":"","routeName":"","isFrame":"1","isCache":"0","menuType":"F","visible":"0","status":"0","perms":"system:role:remove","icon":"#","children":[]},{"createBy":null,"createTime":"2025-11-19 20:51:20","updateBy":null,"updateTime":null,"remark":null,"menuId":1011,"menuName":"角色导出","parentName":null,"parentId":101,"orderNum":5,"path":"","component":"","query":"","routeName":"","isFrame":"1","isCache":"0","menuType":"F","visible":"0","status":"0","perms":"system:role:export","icon":"#","children":[]},{"createBy":null,"createTime":"2025-11-19 20:51:20","updateBy":null,"updateTime":null,"remark":null,"menuId":1012,"menuName":"菜单查询","parentName":null,"parentId":102,"orderNum":1,"path":"","component":"","query":"","routeName":"","isFrame":"1","isCache":"0","menuType":"F","visible":"0","status":"0","perms":"system:menu:query","icon":"#","children":[]},{"createBy":null,"createTime":"2025-11-19 20:51:20","updateBy":null,"updateTime":null,"remark":null,"menuId":1013,"menuName":"菜单新增","parentName":null,"parentId":102,"orderNum":2,"path":"","component":"","query":"","routeName":"","isFrame":"1","isCache":"0","menuType":"F","visible":"0","status":"0","perms":"system:menu:add","icon":"#","children":[]},{"createBy":null,"createTime":"2025-11-19 20:51:20","updateBy":null,"updateTime":null,"remark":null,"menuId":1014,"menuName":"菜单修改","parentName":null,"parentId":102,"orderNum":3,"path":"","component":"","query":"","routeName":"","isFrame":"1","isCache":"0","menuType":"F","visible":"0","status":"0","perms":"system:menu:edit","icon":"#","children":[]},{"createBy":null,"createTime":"2025-11-19 20:51:20","updateBy":null,"updateTime":null,"remark":null,"menuId":1015,"menuName":"菜单删除","parentName":null,"parentId":102,"orderNum":4,"path":"","component":"","query":"","routeName":"","isFrame":"1","isCache":"0","menuType":"F","visible":"0","status":"0","perms":"system:menu:remove","icon":"#","children":[]},{"createBy":null,"createTime":"2025-11-19 20:51:21","updateBy":null,"updateTime":null,"remark":null,"menuId":1016,"menuName":"部门查询","parentName":null,"parentId":103,"orderNum":1,"path":"","component":"","query":"","routeName":"","isFrame":"1","isCache":"0","menuType":"F","visible":"0","status":"0","perms":"system:dept:query","icon":"#","children":[]},{"createBy":null,"createTime":"2025-11-19 20:51:21","updateBy":null,"updateTime":null,"remark":null,"menuId":1017,"menuName":"部门新增","parentName":null,"parentId":103,"orderNum":2,"path":"","component":"","query":"","routeName":"","isFrame":"1","isCache":"0","menuType":"F","visible":"0","status":"0","perms":"system:dept:add","icon":"#","children":[]},{"createBy":null,"createTime":"2025-11-19 20:51:21","updateBy":null,"updateTime":null,"remark":null,"menuId":1018,"menuName":"部门修改","parentName":null,"parentId":103,"orderNum":3,"path":"","component":"","query":"","routeName":"","isFrame":"1","isCache":"0","menuType":"F","visible":"0","status":"0","perms":"system:dept:edit","icon":"#","children":[]},{"createBy":null,"createTime":"2025-11-19 20:51:21","updateBy":null,"updateTime":null,"remark":null,"menuId":1019,"menuName":"部门删除","parentName":null,"parentId":103,"orderNum":4,"path":"","component":"","query":"","routeName":"","isFrame":"1","isCache":"0","menuType":"F","visible":"0","status":"0","perms":"system:dept:remove","icon":"#","children":[]},{"createBy":null,"createTime":"2025-11-19 20:51:21","updateBy":null,"updateTime":null,"remark":null,"menuId":1020,"menuName":"岗位查询","parentName":null,"parentId":104,"orderNum":1,"path":"","component":"","query":"","routeName":"","isFrame":"1","isCache":"0","menuType":"F","visible":"0","status":"0","perms":"system:post:query","icon":"#","children":[]},{"createBy":null,"createTime":"2025-11-19 20:51:21","updateBy":null,"updateTime":null,"remark":null,"menuId":1021,"menuName":"岗位新增","parentName":null,"parentId":104,"orderNum":2,"path":"","component":"","query":"","routeName":"","isFrame":"1","isCache":"0","menuType":"F","visible":"0","status":"0","perms":"system:post:add","icon":"#","children":[]},{"createBy":null,"createTime":"2025-11-19 20:51:21","updateBy":null,"updateTime":null,"remark":null,"menuId":1022,"menuName":"岗位修改","parentName":null,"parentId":104,"orderNum":3,"path":"","component":"","query":"","routeName":"","isFrame":"1","isCache":"0","menuType":"F","visible":"0","status":"0","perms":"system:post:edit","icon":"#","children":[]},{"createBy":null,"createTime":"2025-11-19 20:51:21","updateBy":null,"updateTime":null,"remark":null,"menuId":1023,"menuName":"岗位删除","parentName":null,"parentId":104,"orderNum":4,"path":"","component":"","query":"","routeName":"","isFrame":"1","isCache":"0","menuType":"F","visible":"0","status":"0","perms":"system:post:remove","icon":"#","children":[]},{"createBy":null,"createTime":"2025-11-19 20:51:21","updateBy":null,"updateTime":null,"remark":null,"menuId":1024,"menuName":"岗位导出","parentName":null,"parentId":104,"orderNum":5,"path":"","component":"","query":"","routeName":"","isFrame":"1","isCache":"0","menuType":"F","visible":"0","status":"0","perms":"system:post:export","icon":"#","children":[]},{"createBy":null,"createTime":"2025-11-19 20:51:21","updateBy":null,"updateTime":null,"remark":null,"menuId":1025,"menuName":"字典查询","parentName":null,"parentId":105,"orderNum":1,"path":"#","component":"","query":"","routeName":"","isFrame":"1","isCache":"0","menuType":"F","visible":"0","status":"0","perms":"system:dict:query","icon":"#","children":[]},{"createBy":null,"createTime":"2025-11-19 20:51:21","updateBy":null,"updateTime":null,"remark":null,"menuId":1026,"menuName":"字典新增","parentName":null,"parentId":105,"orderNum":2,"path":"#","component":"","query":"","routeName":"","isFrame":"1","isCache":"0","menuType":"F","visible":"0","status":"0","perms":"system:dict:add","icon":"#","children":[]},{"createBy":null,"createTime":"2025-11-19 20:51:21","updateBy":null,"updateTime":null,"remark":null,"menuId":1027,"menuName":"字典修改","parentName":null,"parentId":105,"orderNum":3,"path":"#","component":"","query":"","routeName":"","isFrame":"1","isCache":"0","menuType":"F","visible":"0","status":"0","perms":"system:dict:edit","icon":"#","children":[]},{"createBy":null,"createTime":"2025-11-19 20:51:21","updateBy":null,"updateTime":null,"remark":null,"menuId":1028,"menuName":"字典删除","parentName":null,"parentId":105,"orderNum":4,"path":"#","component":"","query":"","routeName":"","isFrame":"1","isCache":"0","menuType":"F","visible":"0","status":"0","perms":"system:dict:remove","icon":"#","children":[]},{"createBy":null,"createTime":"2025-11-19 20:51:21","updateBy":null,"updateTime":null,"remark":null,"menuId":1029,"menuName":"字典导出","parentName":null,"parentId":105,"orderNum":5,"path":"#","component":"","query":"","routeName":"","isFrame":"1","isCache":"0","menuType":"F","visible":"0","status":"0","perms":"system:dict:export","icon":"#","children":[]},{"createBy":null,"createTime":"2025-11-19 20:51:21","updateBy":null,"updateTime":null,"remark":null,"menuId":1030,"menuName":"参数查询","parentName":null,"parentId":106,"orderNum":1,"path":"#","component":"","query":"","routeName":"","isFrame":"1","isCache":"0","menuType":"F","visible":"0","status":"0","perms":"system:config:query","icon":"#","children":[]},{"createBy":null,"createTime":"2025-11-19 20:51:21","updateBy":null,"updateTime":null,"remark":null,"menuId":1031,"menuName":"参数新增","parentName":null,"parentId":106,"orderNum":2,"path":"#","component":"","query":"","routeName":"","isFrame":"1","isCache":"0","menuType":"F","visible":"0","status":"0","perms":"system:config:add","icon":"#","children":[]},{"createBy":null,"createTime":"2025-11-19 20:51:21","updateBy":null,"updateTime":null,"remark":null,"menuId":1032,"menuName":"参数修改","parentName":null,"parentId":106,"orderNum":3,"path":"#","component":"","query":"","routeName":"","isFrame":"1","isCache":"0","menuType":"F","visible":"0","status":"0","perms":"system:config:edit","icon":"#","children":[]},{"createBy":null,"createTime":"2025-11-19 20:51:21","updateBy":null,"updateTime":null,"remark":null,"menuId":1033,"menuName":"参数删除","parentName":null,"parentId":106,"orderNum":4,"path":"#","component":"","query":"","routeName":"","isFrame":"1","isCache":"0","menuType":"F","visible":"0","status":"0","perms":"system:config:remove","icon":"#","children":[]},{"createBy":null,"createTime":"2025-11-19 20:51:21","updateBy":null,"updateTime":null,"remark":null,"menuId":1034,"menuName":"参数导出","parentName":null,"parentId":106,"orderNum":5,"path":"#","component":"","query":"","routeName":"","isFrame":"1","isCache":"0","menuType":"F","visible":"0","status":"0","perms":"system:config:export","icon":"#","children":[]},{"createBy":null,"createTime":"2025-11-19 20:51:21","updateBy":null,"updateTime":null,"remark":null,"menuId":1035,"menuName":"公告查询","parentName":null,"parentId":107,"orderNum":1,"path":"#","component":"","query":"","routeName":"","isFrame":"1","isCache":"0","menuType":"F","visible":"0","status":"0","perms":"system:notice:query","icon":"#","children":[]},{"createBy":null,"createTime":"2025-11-19 20:51:21","updateBy":null,"updateTime":null,"remark":null,"menuId":1036,"menuName":"公告新增","parentName":null,"parentId":107,"orderNum":2,"path":"#","component":"","query":"","routeName":"","isFrame":"1","isCache":"0","menuType":"F","visible":"0","status":"0","perms":"system:notice:add","icon":"#","children":[]},{"createBy":null,"createTime":"2025-11-19 20:51:21","updateBy":null,"updateTime":null,"remark":null,"menuId":1037,"menuName":"公告修改","parentName":null,"parentId":107,"orderNum":3,"path":"#","component":"","query":"","routeName":"","isFrame":"1","isCache":"0","menuType":"F","visible":"0","status":"0","perms":"system:notice:edit","icon":"#","children":[]},{"createBy":null,"createTime":"2025-11-19 20:51:21","updateBy":null,"updateTime":null,"remark":null,"menuId":1038,"menuName":"公告删除","parentName":null,"parentId":107,"orderNum":4,"path":"#","component":"","query":"","routeName":"","isFrame":"1","isCache":"0","menuType":"F","visible":"0","status":"0","perms":"system:notice:remove","icon":"#","children":[]},{"createBy":null,"createTime":"2025-11-19 20:51:20","updateBy":null,"updateTime":null,"remark":null,"menuId":500,"menuName":"操作日志","parentName":null,"parentId":108,"orderNum":1,"path":"operlog","component":"monitor/operlog/index","query":"","routeName":"","isFrame":"1","isCache":"0","menuType":"C","visible":"0","status":"0","perms":"monitor:operlog:list","icon":"form","children":[]},{"createBy":null,"createTime":"2025-11-19 20:51:20","updateBy":null,"updateTime":null,"remark":null,"menuId":501,"menuName":"登录日志","parentName":null,"parentId":108,"orderNum":2,"path":"logininfor","component":"monitor/logininfor/index","query":"","routeName":"","isFrame":"1","isCache":"0","menuType":"C","visible":"0","status":"0","perms":"monitor:logininfor:list","icon":"logininfor","children":[]},{"createBy":null,"createTime":"2025-11-19 20:51:22","updateBy":null,"updateTime":null,"remark":null,"menuId":1046,"menuName":"在线查询","parentName":null,"parentId":109,"orderNum":1,"path":"#","component":"","query":"","routeName":"","isFrame":"1","isCache":"0","menuType":"F","visible":"0","status":"0","perms":"monitor:online:query","icon":"#","children":[]},{"createBy":null,"createTime":"2025-11-19 20:51:22","updateBy":null,"updateTime":null,"remark":null,"menuId":1047,"menuName":"批量强退","parentName":null,"parentId":109,"orderNum":2,"path":"#","component":"","query":"","routeName":"","isFrame":"1","isCache":"0","menuType":"F","visible":"0","status":"0","perms":"monitor:online:batchLogout","icon":"#","children":[]},{"createBy":null,"createTime":"2025-11-19 20:51:22","updateBy":null,"updateTime":null,"remark":null,"menuId":1048,"menuName":"单条强退","parentName":null,"parentId":109,"orderNum":3,"path":"#","component":"","query":"","routeName":"","isFrame":"1","isCache":"0","menuType":"F","visible":"0","status":"0","perms":"monitor:online:forceLogout","icon":"#","children":[]},{"createBy":null,"createTime":"2025-11-19 20:51:22","updateBy":null,"updateTime":null,"remark":null,"menuId":1049,"menuName":"任务查询","parentName":null,"parentId":110,"orderNum":1,"path":"#","component":"","query":"","routeName":"","isFrame":"1","isCache":"0","menuType":"F","visible":"0","status":"0","perms":"monitor:job:query","icon":"#","children":[]},{"createBy":null,"createTime":"2025-11-19 20:51:22","updateBy":null,"updateTime":null,"remark":null,"menuId":1050,"menuName":"任务新增","parentName":null,"parentId":110,"orderNum":2,"path":"#","component":"","query":"","routeName":"","isFrame":"1","isCache":"0","menuType":"F","visible":"0","status":"0","perms":"monitor:job:add","icon":"#","children":[]},{"createBy":null,"createTime":"2025-11-19 20:51:22","updateBy":null,"updateTime":null,"remark":null,"menuId":1051,"menuName":"任务修改","parentName":null,"parentId":110,"orderNum":3,"path":"#","component":"","query":"","routeName":"","isFrame":"1","isCache":"0","menuType":"F","visible":"0","status":"0","perms":"monitor:job:edit","icon":"#","children":[]},{"createBy":null,"createTime":"2025-11-19 20:51:22","updateBy":null,"updateTime":null,"remark":null,"menuId":1052,"menuName":"任务删除","parentName":null,"parentId":110,"orderNum":4,"path":"#","component":"","query":"","routeName":"","isFrame":"1","isCache":"0","menuType":"F","visible":"0","status":"0","perms":"monitor:job:remove","icon":"#","children":[]},{"createBy":null,"createTime":"2025-11-19 20:51:22","updateBy":null,"updateTime":null,"remark":null,"menuId":1053,"menuName":"状态修改","parentName":null,"parentId":110,"orderNum":5,"path":"#","component":"","query":"","routeName":"","isFrame":"1","isCache":"0","menuType":"F","visible":"0","status":"0","perms":"monitor:job:changeStatus","icon":"#","children":[]},{"createBy":null,"createTime":"2025-11-19 20:51:22","updateBy":null,"updateTime":null,"remark":null,"menuId":1054,"menuName":"任务导出","parentName":null,"parentId":110,"orderNum":6,"path":"#","component":"","query":"","routeName":"","isFrame":"1","isCache":"0","menuType":"F","visible":"0","status":"0","perms":"monitor:job:export","icon":"#","children":[]},{"createBy":null,"createTime":"2025-11-19 20:51:22","updateBy":null,"updateTime":null,"remark":null,"menuId":1055,"menuName":"生成查询","parentName":null,"parentId":116,"orderNum":1,"path":"#","component":"","query":"","routeName":"","isFrame":"1","isCache":"0","menuType":"F","visible":"0","status":"0","perms":"tool:gen:query","icon":"#","children":[]},{"createBy":null,"createTime":"2025-11-19 20:51:22","updateBy":null,"updateTime":null,"remark":null,"menuId":1056,"menuName":"生成修改","parentName":null,"parentId":116,"orderNum":2,"path":"#","component":"","query":"","routeName":"","isFrame":"1","isCache":"0","menuType":"F","visible":"0","status":"0","perms":"tool:gen:edit","icon":"#","children":[]},{"createBy":null,"createTime":"2025-11-19 20:51:22","updateBy":null,"updateTime":null,"remark":null,"menuId":1057,"menuName":"生成删除","parentName":null,"parentId":116,"orderNum":3,"path":"#","component":"","query":"","routeName":"","isFrame":"1","isCache":"0","menuType":"F","visible":"0","status":"0","perms":"tool:gen:remove","icon":"#","children":[]},{"createBy":null,"createTime":"2025-11-19 20:51:22","updateBy":null,"updateTime":null,"remark":null,"menuId":1058,"menuName":"导入代码","parentName":null,"parentId":116,"orderNum":4,"path":"#","component":"","query":"","routeName":"","isFrame":"1","isCache":"0","menuType":"F","visible":"0","status":"0","perms":"tool:gen:import","icon":"#","children":[]},{"createBy":null,"createTime":"2025-11-19 20:51:22","updateBy":null,"updateTime":null,"remark":null,"menuId":1059,"menuName":"预览代码","parentName":null,"parentId":116,"orderNum":5,"path":"#","component":"","query":"","routeName":"","isFrame":"1","isCache":"0","menuType":"F","visible":"0","status":"0","perms":"tool:gen:preview","icon":"#","children":[]},{"createBy":null,"createTime":"2025-11-19 20:51:22","updateBy":null,"updateTime":null,"remark":null,"menuId":1060,"menuName":"生成代码","parentName":null,"parentId":116,"orderNum":6,"path":"#","component":"","query":"","routeName":"","isFrame":"1","isCache":"0","menuType":"F","visible":"0","status":"0","perms":"tool:gen:code","icon":"#","children":[]},{"createBy":null,"createTime":"2025-11-19 20:51:21","updateBy":null,"updateTime":null,"remark":null,"menuId":1039,"menuName":"操作查询","parentName":null,"parentId":500,"orderNum":1,"path":"#","component":"","query":"","routeName":"","isFrame":"1","isCache":"0","menuType":"F","visible":"0","status":"0","perms":"monitor:operlog:query","icon":"#","children":[]},{"createBy":null,"createTime":"2025-11-19 20:51:21","updateBy":null,"updateTime":null,"remark":null,"menuId":1040,"menuName":"操作删除","parentName":null,"parentId":500,"orderNum":2,"path":"#","component":"","query":"","routeName":"","isFrame":"1","isCache":"0","menuType":"F","visible":"0","status":"0","perms":"monitor:operlog:remove","icon":"#","children":[]},{"createBy":null,"createTime":"2025-11-19 20:51:22","updateBy":null,"updateTime":null,"remark":null,"menuId":1041,"menuName":"日志导出","parentName":null,"parentId":500,"orderNum":3,"path":"#","component":"","query":"","routeName":"","isFrame":"1","isCache":"0","menuType":"F","visible":"0","status":"0","perms":"monitor:operlog:export","icon":"#","children":[]},{"createBy":null,"createTime":"2025-11-19 20:51:22","updateBy":null,"updateTime":null,"remark":null,"menuId":1042,"menuName":"登录查询","parentName":null,"parentId":501,"orderNum":1,"path":"#","component":"","query":"","routeName":"","isFrame":"1","isCache":"0","menuType":"F","visible":"0","status":"0","perms":"monitor:logininfor:query","icon":"#","children":[]},{"createBy":null,"createTime":"2025-11-19 20:51:22","updateBy":null,"updateTime":null,"remark":null,"menuId":1043,"menuName":"登录删除","parentName":null,"parentId":501,"orderNum":2,"path":"#","component":"","query":"","routeName":"","isFrame":"1","isCache":"0","menuType":"F","visible":"0","status":"0","perms":"monitor:logininfor:remove","icon":"#","children":[]},{"createBy":null,"createTime":"2025-11-19 20:51:22","updateBy":null,"updateTime":null,"remark":null,"menuId":1044,"menuName":"日志导出","parentName":null,"parentId":501,"orderNum":3,"path":"#","component":"","query":"","routeName":"","isFrame":"1","isCache":"0","menuType":"F","visible":"0","status":"0","perms":"monitor:logininfor:export","icon":"#","children":[]},{"createBy":null,"createTime":"2025-11-19 20:51:22","updateBy":null,"updateTime":null,"remark":null,"menuId":1045,"menuName":"账户解锁","parentName":null,"parentId":501,"orderNum":4,"path":"#","component":"","query":"","routeName":"","isFrame":"1","isCache":"0","menuType":"F","visible":"0","status":"0","perms":"monitor:logininfor:unlock","icon":"#","children":[]},{"createBy":null,"createTime":"2025-11-25 17:33:33","updateBy":null,"updateTime":null,"remark":null,"menuId":2002,"menuName":"客户管理","parentName":null,"parentId":2000,"orderNum":1,"path":"manage","component":"customer/manage/index","query":null,"routeName":"","isFrame":"1","isCache":"0","menuType":"C","visible":"0","status":"0","perms":"customer:manage:list","icon":"people","children":[]},{"createBy":null,"createTime":"2025-11-25 17:35:49","updateBy":null,"updateTime":null,"remark":null,"menuId":2003,"menuName":"客户审核","parentName":null,"parentId":2000,"orderNum":2,"path":"review","component":"customer/review/index","query":null,"routeName":"","isFrame":"1","isCache":"0","menuType":"C","visible":"0","status":"0","perms":"customer:review:list","icon":"checkbox","children":[]},{"createBy":null,"createTime":"2025-11-27 14:02:54","updateBy":null,"updateTime":null,"remark":null,"menuId":2011,"menuName":"课题组管理","parentName":null,"parentId":2000,"orderNum":3,"path":"research_group","component":"customer/research_group/index","query":null,"routeName":"","isFrame":"1","isCache":"0","menuType":"C","visible":"0","status":"0","perms":"customer:research_group:list","icon":"job","children":[]},{"createBy":null,"createTime":"2025-11-27 17:41:31","updateBy":null,"updateTime":null,"remark":null,"menuId":2013,"menuName":"客户课题组","parentName":null,"parentId":2000,"orderNum":4,"path":"research","component":"customer/research/index","query":null,"routeName":"research","isFrame":"1","isCache":"0","menuType":"C","visible":"0","status":"0","perms":"customer:research:list","icon":"table","children":[]},{"createBy":null,"createTime":"2025-11-26 18:11:57","updateBy":null,"updateTime":null,"remark":null,"menuId":2004,"menuName":"客户查询","parentName":null,"parentId":2002,"orderNum":1,"path":"","component":null,"query":null,"routeName":"","isFrame":"1","isCache":"0","menuType":"F","visible":"0","status":"0","perms":"customer:manage:query","icon":"#","children":[]},{"createBy":null,"createTime":"2025-11-26 18:24:02","updateBy":null,"updateTime":null,"remark":null,"menuId":2005,"menuName":"客户新增","parentName":null,"parentId":2002,"orderNum":2,"path":"","component":null,"query":null,"routeName":"","isFrame":"1","isCache":"0","menuType":"F","visible":"0","status":"0","perms":"customer:manage:add","icon":"#","children":[]},{"createBy":null,"createTime":"2025-11-26 18:24:17","updateBy":null,"updateTime":null,"remark":null,"menuId":2006,"menuName":"客户编辑","parentName":null,"parentId":2002,"orderNum":3,"path":"","component":null,"query":null,"routeName":"","isFrame":"1","isCache":"0","menuType":"F","visible":"0","status":"0","perms":"customer:manage:edit","icon":"#","children":[]},{"createBy":null,"createTime":"2025-11-26 18:24:32","updateBy":null,"updateTime":null,"remark":null,"menuId":2007,"menuName":"客户删除","parentName":null,"parentId":2002,"orderNum":4,"path":"","component":null,"query":null,"routeName":"","isFrame":"1","isCache":"0","menuType":"F","visible":"0","status":"0","perms":"customer:manage:remove","icon":"#","children":[]},{"createBy":null,"createTime":"2025-11-27 13:51:09","updateBy":null,"updateTime":null,"remark":null,"menuId":2008,"menuName":"删除","parentName":null,"parentId":2003,"orderNum":1,"path":"","component":null,"query":null,"routeName":"","isFrame":"1","isCache":"0","menuType":"F","visible":"0","status":"0","perms":"customer:review:remove","icon":"#","children":[]},{"createBy":null,"createTime":"2025-11-27 13:51:39","updateBy":null,"updateTime":null,"remark":null,"menuId":2009,"menuName":"审核","parentName":null,"parentId":2003,"orderNum":2,"path":"customer:review:remove","component":null,"query":null,"routeName":"","isFrame":"1","isCache":"0","menuType":"F","visible":"0","status":"0","perms":"customer:review:edit","icon":"#","children":[]},{"createBy":null,"createTime":"2025-11-27 13:52:11","updateBy":null,"updateTime":null,"remark":null,"menuId":2010,"menuName":"查询","parentName":null,"parentId":2003,"orderNum":3,"path":"","component":null,"query":null,"routeName":"","isFrame":"1","isCache":"0","menuType":"F","visible":"0","status":"0","perms":"customer:review:query","icon":"#","children":[]},{"createBy":null,"createTime":"2025-11-27 14:03:46","updateBy":null,"updateTime":null,"remark":null,"menuId":2012,"menuName":"查询","parentName":null,"parentId":2011,"orderNum":1,"path":"","component":null,"query":null,"routeName":"","isFrame":"1","isCache":"0","menuType":"F","visible":"0","status":"0","perms":"customer:research_group:query","icon":"#","children":[]},{"createBy":null,"createTime":"2025-11-27 17:42:25","updateBy":null,"updateTime":null,"remark":null,"menuId":2014,"menuName":"查询","parentName":null,"parentId":2013,"orderNum":1,"path":"","component":null,"query":null,"routeName":"","isFrame":"1","isCache":"0","menuType":"F","visible":"0","status":"0","perms":"customer:research:query","icon":"#","children":[]},{"createBy":null,"createTime":"2025-11-27 17:42:40","updateBy":null,"updateTime":null,"remark":null,"menuId":2015,"menuName":"添加","parentName":null,"parentId":2013,"orderNum":2,"path":"","component":null,"query":null,"routeName":"","isFrame":"1","isCache":"0","menuType":"F","visible":"0","status":"0","perms":"customer:research:add","icon":"#","children":[]},{"createBy":null,"createTime":"2025-11-27 17:43:01","updateBy":null,"updateTime":null,"remark":null,"menuId":2016,"menuName":"编辑","parentName":null,"parentId":2013,"orderNum":3,"path":"","component":null,"query":null,"routeName":"","isFrame":"1","isCache":"0","menuType":"F","visible":"0","status":"0","perms":"customer:research:edit","icon":"#","children":[]},{"createBy":null,"createTime":"2025-11-27 17:43:15","updateBy":null,"updateTime":null,"remark":null,"menuId":2017,"menuName":"删除","parentName":null,"parentId":2013,"orderNum":4,"path":"","component":null,"query":null,"routeName":"","isFrame":"1","isCache":"0","menuType":"F","visible":"0","status":"0","perms":"customer:research:remove","icon":"#","children":[]},{"createBy":null,"createTime":"2025-11-28 13:24:35","updateBy":null,"updateTime":null,"remark":null,"menuId":2020,"menuName":"订单管理","parentName":null,"parentId":2018,"orderNum":2,"path":"order","component":"sequencing/order/index","query":null,"routeName":"","isFrame":"1","isCache":"0","menuType":"C","visible":"0","status":"0","perms":"sequencing:order:list","icon":"list","children":[]},{"createBy":null,"createTime":"2025-11-28 13:26:49","updateBy":null,"updateTime":null,"remark":null,"menuId":2021,"menuName":"模板浏览","parentName":null,"parentId":2018,"orderNum":3,"path":"template","component":"sequencing/template/index","query":null,"routeName":"","isFrame":"1","isCache":"0","menuType":"C","visible":"1","status":"0","perms":"sequencing:template:list","icon":"table","children":[]},{"createBy":null,"createTime":"2025-11-28 14:49:15","updateBy":null,"updateTime":null,"remark":null,"menuId":2025,"menuName":"测序样品","parentName":null,"parentId":2018,"orderNum":4,"path":"samples","component":"sequencing/samples/index","query":null,"routeName":"","isFrame":"1","isCache":"0","menuType":"C","visible":"0","status":"0","perms":"sequencing:samples:list","icon":"row","children":[]},{"createBy":null,"createTime":"2025-11-28 14:59:12","updateBy":null,"updateTime":null,"remark":null,"menuId":2026,"menuName":"引物管理","parentName":null,"parentId":2018,"orderNum":5,"path":"primer","component":"sequencing/primer/index","query":null,"routeName":"","isFrame":"1","isCache":"0","menuType":"C","visible":"1","status":"0","perms":"sequencing:primer:list","icon":"slider","children":[]},{"createBy":null,"createTime":"2025-11-28 15:00:15","updateBy":null,"updateTime":null,"remark":null,"menuId":2027,"menuName":"返还管理","parentName":null,"parentId":2018,"orderNum":6,"path":"return","component":"sequencing/return/index","query":null,"routeName":"","isFrame":"1","isCache":"0","menuType":"C","visible":"0","status":"0","perms":"sequencing:return:list","icon":"more-up","children":[]},{"createBy":null,"createTime":"2025-11-28 15:01:20","updateBy":null,"updateTime":null,"remark":null,"menuId":2028,"menuName":"模板排版","parentName":null,"parentId":2018,"orderNum":7,"path":"schedule","component":"sequencing/schedule/index","query":null,"routeName":"","isFrame":"1","isCache":"0","menuType":"C","visible":"0","status":"0","perms":"sequencing:schedule:list","icon":"date","children":[]},{"createBy":null,"createTime":"2025-11-28 15:02:07","updateBy":null,"updateTime":null,"remark":null,"menuId":2029,"menuName":"模板生产","parentName":null,"parentId":2018,"orderNum":8,"path":"production","component":"sequencing/production/index","query":null,"routeName":"","isFrame":"1","isCache":"0","menuType":"C","visible":"0","status":"0","perms":"sequencing:production:list","icon":"time","children":[]},{"createBy":null,"createTime":"2025-11-28 15:04:00","updateBy":null,"updateTime":null,"remark":null,"menuId":2030,"menuName":"模板邮件","parentName":null,"parentId":2018,"orderNum":9,"path":"email","component":"sequencing/email/index","query":null,"routeName":"","isFrame":"1","isCache":"0","menuType":"C","visible":"0","status":"0","perms":"sequencing:email:list","icon":"email","children":[]},{"createBy":null,"createTime":"2025-11-28 15:09:52","updateBy":null,"updateTime":null,"remark":null,"menuId":2031,"menuName":"样品补送","parentName":null,"parentId":2018,"orderNum":10,"path":"resend","component":"sequencing/resend/index","query":null,"routeName":"","isFrame":"1","isCache":"0","menuType":"C","visible":"0","status":"0","perms":"sequencing:resend:list","icon":"guide","children":[]},{"createBy":null,"createTime":"2025-11-28 15:10:53","updateBy":null,"updateTime":null,"remark":null,"menuId":2032,"menuName":"样品不足邮件","parentName":null,"parentId":2018,"orderNum":11,"path":"resend_email","component":"sequencing/resend_email/index","query":null,"routeName":"","isFrame":"1","isCache":"0","menuType":"C","visible":"0","status":"0","perms":"sequencing:resend_email:list","icon":"email","children":[]},{"createBy":null,"createTime":"2026-03-28 20:11:32","updateBy":null,"updateTime":null,"remark":null,"menuId":2038,"menuName":"反应生产","parentName":null,"parentId":2018,"orderNum":12,"path":"reaction","component":"sequencing/reaction/index","query":null,"routeName":"","isFrame":"1","isCache":"0","menuType":"C","visible":"0","status":"0","perms":"sequencing:reaction:list","icon":"enter","children":[]},{"createBy":null,"createTime":"2026-03-28 20:43:32","updateBy":null,"updateTime":null,"remark":null,"menuId":2041,"menuName":"反应预做","parentName":null,"parentId":2018,"orderNum":13,"path":"prereaction","component":"sequencing/prereaction/index","query":null,"routeName":"","isFrame":"1","isCache":"0","menuType":"C","visible":"0","status":"0","perms":"sequencing:prereaction:list","icon":"monitor","children":[]},{"createBy":null,"createTime":"2026-03-28 20:46:22","updateBy":null,"updateTime":null,"remark":null,"menuId":2043,"menuName":"测序文件","parentName":null,"parentId":2018,"orderNum":14,"path":"sequencing-file","component":"sequencing/file/index","query":null,"routeName":"","isFrame":"1","isCache":"0","menuType":"C","visible":"0","status":"0","perms":"sequencing:file:list","icon":"documentation","children":[]},{"createBy":null,"createTime":"2026-03-28 20:45:11","updateBy":null,"updateTime":null,"remark":null,"menuId":2042,"menuName":"报告生产","parentName":null,"parentId":2018,"orderNum":15,"path":"report-produce","component":"sequencing/report/index","query":null,"routeName":"","isFrame":"1","isCache":"0","menuType":"C","visible":"0","status":"0","perms":"sequencing:report:list","icon":"pdf","children":[]},{"createBy":null,"createTime":"2026-03-28 20:48:01","updateBy":null,"updateTime":null,"remark":null,"menuId":2045,"menuName":"报告邮件","parentName":null,"parentId":2018,"orderNum":16,"path":"report-email","component":"sequencing/report-email/index","query":null,"routeName":"","isFrame":"1","isCache":"0","menuType":"C","visible":"0","status":"0","perms":"sequencing:reportemail:list","icon":"email","children":[]},{"createBy":null,"createTime":"2026-04-06 17:18:46","updateBy":null,"updateTime":null,"remark":null,"menuId":2046,"menuName":"订单出库","parentName":null,"parentId":2018,"orderNum":17,"path":"orderout","component":"sequencing/orderout/index","query":null,"routeName":"","isFrame":"1","isCache":"0","menuType":"C","visible":"0","status":"0","perms":"sequencing:orderout:list","icon":"enter","children":[]},{"createBy":null,"createTime":"2026-04-06 17:19:37","updateBy":null,"updateTime":null,"remark":null,"menuId":2047,"menuName":"订单完成","parentName":null,"parentId":2018,"orderNum":18,"path":"order-complete","component":"sequencing/order-complete/index","query":null,"routeName":"","isFrame":"1","isCache":"0","menuType":"C","visible":"0","status":"0","perms":"sequencing:order-complete:list","icon":"select","children":[]},{"createBy":null,"createTime":"2026-04-06 17:20:01","updateBy":null,"updateTime":null,"remark":null,"menuId":2048,"menuName":"订单价格","parentName":null,"parentId":2018,"orderNum":19,"path":"order-price","component":"sequencing/order-price/index","query":null,"routeName":"","isFrame":"1","isCache":"0","menuType":"C","visible":"0","status":"0","perms":"sequencing:order-price:list","icon":"money","children":[]},{"createBy":null,"createTime":"2026-04-06 17:22:09","updateBy":null,"updateTime":null,"remark":null,"menuId":2049,"menuName":"测序入财务","parentName":null,"parentId":2018,"orderNum":21,"path":"into-finance","component":"sequencing/into-finance/index","query":null,"routeName":"","isFrame":"1","isCache":"0","menuType":"C","visible":"0","status":"0","perms":"sequencing:into-finance:list","icon":"shopping","children":[]},{"createBy":null,"createTime":"2026-04-06 17:23:33","updateBy":null,"updateTime":null,"remark":null,"menuId":2050,"menuName":"毛细管跟踪","parentName":null,"parentId":2018,"orderNum":22,"path":"capillary-tracking","component":"sequencing/capillary-tracking/index","query":null,"routeName":"","isFrame":"1","isCache":"0","menuType":"C","visible":"0","status":"0","perms":"sequencing:capillary-tracking:list","icon":"user","children":[]},{"createBy":null,"createTime":"2026-04-06 17:24:26","updateBy":null,"updateTime":null,"remark":null,"menuId":2051,"menuName":"订单返回确认","parentName":null,"parentId":2018,"orderNum":23,"path":"order-confirm","component":"sequencing/order-confirm/index","query":null,"routeName":"","isFrame":"1","isCache":"0","menuType":"C","visible":"0","status":"0","perms":"sequencing:order-confirm:list","icon":"validCode","children":[]},{"createBy":null,"createTime":"2026-03-28 20:47:32","updateBy":null,"updateTime":null,"remark":null,"menuId":2044,"menuName":"拼接状态","parentName":null,"parentId":2018,"orderNum":26,"path":"alignment","component":"sequencing/alignment/index","query":null,"routeName":"","isFrame":"1","isCache":"0","menuType":"C","visible":"1","status":"0","perms":"sequencing:alignment:list","icon":"more-up","children":[]},{"createBy":null,"createTime":"2025-11-28 11:44:37","updateBy":null,"updateTime":null,"remark":null,"menuId":2019,"menuName":"测序交接","parentName":null,"parentId":2018,"orderNum":27,"path":"handover","component":"sequencing/handover/index","query":null,"routeName":"","isFrame":"1","isCache":"0","menuType":"C","visible":"1","status":"0","perms":"sequencing:handover:list","icon":"job","children":[]},{"createBy":null,"createTime":"2025-11-28 14:42:13","updateBy":null,"updateTime":null,"remark":null,"menuId":2022,"menuName":"查询","parentName":null,"parentId":2019,"orderNum":1,"path":"","component":null,"query":null,"routeName":"","isFrame":"1","isCache":"0","menuType":"F","visible":"0","status":"0","perms":"sequencing:handover:query","icon":"#","children":[]},{"createBy":null,"createTime":"2025-11-28 14:42:43","updateBy":null,"updateTime":null,"remark":null,"menuId":2023,"menuName":"查询","parentName":null,"parentId":2020,"orderNum":1,"path":"","component":null,"query":null,"routeName":"","isFrame":"1","isCache":"0","menuType":"F","visible":"0","status":"0","perms":"sequencing:order:query","icon":"#","children":[]},{"createBy":null,"createTime":"2025-11-28 14:43:04","updateBy":null,"updateTime":null,"remark":null,"menuId":2024,"menuName":"查询","parentName":null,"parentId":2021,"orderNum":1,"path":"","component":null,"query":null,"routeName":"","isFrame":"1","isCache":"0","menuType":"F","visible":"0","status":"0","perms":"sequencing:template:query","icon":"#","children":[]},{"createBy":null,"createTime":"2026-01-06 23:39:54","updateBy":null,"updateTime":null,"remark":null,"menuId":2034,"menuName":"测序订单历史数据","parentName":null,"parentId":2033,"orderNum":1,"path":"sequenceorder","component":"history/sequenceorder/index","query":null,"routeName":"","isFrame":"1","isCache":"0","menuType":"C","visible":"0","status":"0","perms":"history:sequenceorder:list","icon":"example","children":[]},{"createBy":null,"createTime":"2026-01-06 23:43:30","updateBy":null,"updateTime":null,"remark":null,"menuId":2035,"menuName":"测序样品历史","parentName":null,"parentId":2033,"orderNum":2,"path":"sequencesample","component":"history/sequencesample/index","query":null,"routeName":"","isFrame":"1","isCache":"0","menuType":"C","visible":"0","status":"0","perms":"history:sequencesample:list","icon":"search","children":[]},{"createBy":null,"createTime":"2026-01-06 23:46:39","updateBy":null,"updateTime":null,"remark":null,"menuId":2036,"menuName":"合成订单历史","parentName":null,"parentId":2033,"orderNum":3,"path":"produceorder","component":"history/produceorder/index","query":null,"routeName":"","isFrame":"1","isCache":"0","menuType":"C","visible":"0","status":"0","perms":"history:produceorder:list","icon":"drag","children":[]},{"createBy":null,"createTime":"2026-01-06 23:49:13","updateBy":null,"updateTime":null,"remark":null,"menuId":2037,"menuName":"合成样品历史","parentName":null,"parentId":2033,"orderNum":4,"path":"producesample","component":"history/producesample/index","query":null,"routeName":"","isFrame":"1","isCache":"0","menuType":"C","visible":"0","status":"0","perms":"history:producesample:list","icon":"druid","children":[]},{"createBy":null,"createTime":"2026-04-14 00:08:46","updateBy":null,"updateTime":null,"remark":null,"menuId":2053,"menuName":"合成订单审核","parentName":null,"parentId":2052,"orderNum":1,"path":"audit","component":"synthesis/audit/index","query":null,"routeName":"","isFrame":"1","isCache":"0","menuType":"C","visible":"0","status":"0","perms":"synthesis:audit:list","icon":"peoples","children":[]},{"createBy":null,"createTime":"2026-04-14 00:08:47","updateBy":null,"updateTime":null,"remark":null,"menuId":2054,"menuName":"合成费用","parentName":null,"parentId":2052,"orderNum":2,"path":"fee","component":"synthesis/fee/index","query":null,"routeName":"","isFrame":"1","isCache":"0","menuType":"C","visible":"0","status":"0","perms":"synthesis:fee:list","icon":"money","children":[]},{"createBy":null,"createTime":"2026-04-14 00:08:47","updateBy":null,"updateTime":null,"remark":null,"menuId":2055,"menuName":"合成订单","parentName":null,"parentId":2052,"orderNum":3,"path":"order","component":"synthesis/order/index","query":null,"routeName":"","isFrame":"1","isCache":"0","menuType":"C","visible":"0","status":"0","perms":"synthesis:order:list","icon":"list","children":[]},{"createBy":null,"createTime":"2026-04-14 00:08:47","updateBy":null,"updateTime":null,"remark":null,"menuId":2056,"menuName":"合成样品","parentName":null,"parentId":2052,"orderNum":4,"path":"samples","component":"synthesis/samples/index","query":null,"routeName":"","isFrame":"1","isCache":"0","menuType":"C","visible":"0","status":"0","perms":"synthesis:samples:list","icon":"row","children":[]},{"createBy":null,"createTime":"2026-04-14 00:08:47","updateBy":null,"updateTime":null,"remark":null,"menuId":2057,"menuName":"合成报告邮件","parentName":null,"parentId":2052,"orderNum":5,"path":"report-email","component":"synthesis/report-email/index","query":null,"routeName":"","isFrame":"1","isCache":"0","menuType":"C","visible":"0","status":"0","perms":"synthesis:report-email:list","icon":"email","children":[]},{"createBy":null,"createTime":"2026-04-14 00:08:47","updateBy":null,"updateTime":null,"remark":null,"menuId":2058,"menuName":"图形排版","parentName":null,"parentId":2052,"orderNum":6,"path":"layout","component":"synthesis/layout/index","query":null,"routeName":"","isFrame":"1","isCache":"0","menuType":"C","visible":"0","status":"0","perms":"synthesis:layout:list","icon":"table","children":[]},{"createBy":null,"createTime":"2026-04-14 00:08:47","updateBy":null,"updateTime":null,"remark":null,"menuId":2059,"menuName":"安排合成","parentName":null,"parentId":2052,"orderNum":7,"path":"arrange","component":"synthesis/arrange/index","query":null,"routeName":"","isFrame":"1","isCache":"0","menuType":"C","visible":"0","status":"0","perms":"synthesis:arrange:list","icon":"edit","children":[]},{"createBy":null,"createTime":"2026-04-14 00:08:47","updateBy":null,"updateTime":null,"remark":null,"menuId":2060,"menuName":"合成修饰","parentName":null,"parentId":2052,"orderNum":8,"path":"modify","component":"synthesis/modify/index","query":null,"routeName":"","isFrame":"1","isCache":"0","menuType":"C","visible":"0","status":"0","perms":"synthesis:modify:list","icon":"star","children":[]},{"createBy":null,"createTime":"2026-04-14 00:08:47","updateBy":null,"updateTime":null,"remark":null,"menuId":2061,"menuName":"合成氨解","parentName":null,"parentId":2052,"orderNum":9,"path":"ammonolysis","component":"synthesis/ammonolysis/index","query":null,"routeName":"","isFrame":"1","isCache":"0","menuType":"C","visible":"0","status":"0","perms":"synthesis:ammonolysis:list","icon":"grid","children":[]},{"createBy":null,"createTime":"2026-04-14 00:08:47","updateBy":null,"updateTime":null,"remark":null,"menuId":2062,"menuName":"合成纯化","parentName":null,"parentId":2052,"orderNum":10,"path":"purification","component":"synthesis/purification/index","query":null,"routeName":"","isFrame":"1","isCache":"0","menuType":"C","visible":"0","status":"0","perms":"synthesis:purification:list","icon":"calculator","children":[]},{"createBy":null,"createTime":"2026-04-14 00:08:48","updateBy":null,"updateTime":null,"remark":null,"menuId":2063,"menuName":"合成分装值","parentName":null,"parentId":2052,"orderNum":11,"path":"aliquot-value","component":"synthesis/aliquot-value/index","query":null,"routeName":"","isFrame":"1","isCache":"0","menuType":"C","visible":"0","status":"0","perms":"synthesis:aliquot-value:list","icon":"calculator","children":[]},{"createBy":null,"createTime":"2026-04-14 00:08:48","updateBy":null,"updateTime":null,"remark":null,"menuId":2064,"menuName":"合成分装","parentName":null,"parentId":2052,"orderNum":12,"path":"aliquot","component":"synthesis/aliquot/index","query":null,"routeName":"","isFrame":"1","isCache":"0","menuType":"C","visible":"0","status":"0","perms":"synthesis:aliquot:list","icon":"table","children":[]},{"createBy":null,"createTime":"2026-04-14 00:08:48","updateBy":null,"updateTime":null,"remark":null,"menuId":2065,"menuName":"合成烘干","parentName":null,"parentId":2052,"orderNum":13,"path":"drying","component":"synthesis/drying/index","query":null,"routeName":"","isFrame":"1","isCache":"0","menuType":"C","visible":"0","status":"0","perms":"synthesis:drying:list","icon":"monitor","children":[]},{"createBy":null,"createTime":"2026-04-14 00:08:48","updateBy":null,"updateTime":null,"remark":null,"menuId":2066,"menuName":"合成订单出库","parentName":null,"parentId":2052,"orderNum":14,"path":"orderout","component":"synthesis/orderout/index","query":null,"routeName":"","isFrame":"1","isCache":"0","menuType":"C","visible":"0","status":"0","perms":"synthesis:orderout:list","icon":"enter","children":[]},{"createBy":null,"createTime":"2026-04-14 00:08:48","updateBy":null,"updateTime":null,"remark":null,"menuId":2067,"menuName":"合成订单完成","parentName":null,"parentId":2052,"orderNum":15,"path":"order-complete","component":"synthesis/order-complete/index","query":null,"routeName":"","isFrame":"1","isCache":"0","menuType":"C","visible":"0","status":"0","perms":"synthesis:order-complete:list","icon":"select","children":[]},{"createBy":null,"createTime":"2026-04-14 00:08:48","updateBy":null,"updateTime":null,"remark":null,"menuId":2068,"menuName":"合成入财务","parentName":null,"parentId":2052,"orderNum":16,"path":"into-finance","component":"synthesis/into-finance/index","query":null,"routeName":"","isFrame":"1","isCache":"0","menuType":"C","visible":"0","status":"0","perms":"synthesis:into-finance:list","icon":"shopping","children":[]}]}